odoo/addons/web_sheet_full_width/README.rst
odoo/addons/web_sheet_full_width/__init__.py
odoo/addons/web_sheet_full_width/__manifest__.py
odoo/addons/web_sheet_full_width/i18n/web_sheet_full_width.pot
odoo/addons/web_sheet_full_width/static/description/icon.png
odoo/addons/web_sheet_full_width/static/src/css/web_sheet_full_width.less
odoo/addons/web_sheet_full_width/templates/assets.xml
odoo11_addon_web_sheet_full_width-11.0.1.0.2.dist-info/METADATA
odoo11_addon_web_sheet_full_width-11.0.1.0.2.dist-info/WHEEL
odoo11_addon_web_sheet_full_width-11.0.1.0.2.dist-info/top_level.txt
odoo11_addon_web_sheet_full_width-11.0.1.0.2.dist-info/RECORD
